sk/__init__.py
sk/sk.py
yuanshuang-1.0.1.dist-info/LICENSE
yuanshuang-1.0.1.dist-info/METADATA
yuanshuang-1.0.1.dist-info/WHEEL
yuanshuang-1.0.1.dist-info/top_level.txt
yuanshuang-1.0.1.dist-info/RECORD
