Metadata-Version: 2.1
Name: yuanshuang
Version: 1.0.1
Summary: sk_pg package
Home-page: 
Author: yuanshuang
Author-email: 18872142367@qq.com
Requires-Python: >=3.7
License-File: LICENSE
